codehealthanalyzer/__init__.py
codehealthanalyzer/i18n.py
codehealthanalyzer/analyzers/__init__.py
codehealthanalyzer/analyzers/errors.py
codehealthanalyzer/analyzers/templates.py
codehealthanalyzer/analyzers/violations.py
codehealthanalyzer/cli/__init__.py
codehealthanalyzer/cli/main.py
codehealthanalyzer/reports/__init__.py
codehealthanalyzer/reports/formatter.py
codehealthanalyzer/reports/generator.py
codehealthanalyzer/utils/__init__.py
codehealthanalyzer/utils/categorizer.py
codehealthanalyzer/utils/helpers.py
codehealthanalyzer/utils/validators.py
codehealthanalyzer/web/__init__.py
codehealthanalyzer/web/server.py
codehealthanalyzer/web/static/css/dashboard.css
codehealthanalyzer/web/static/js/dashboard.js
codehealthanalyzer/web/templates/dashboard.html
codehealthanalyzer-1.1.9.dist-info/licenses/LICENSE
codehealthanalyzer-1.1.9.dist-info/METADATA
codehealthanalyzer-1.1.9.dist-info/WHEEL
codehealthanalyzer-1.1.9.dist-info/entry_points.txt
codehealthanalyzer-1.1.9.dist-info/top_level.txt
codehealthanalyzer-1.1.9.dist-info/RECORD
