Metadata-Version: 2.4
Name: codehealthanalyzer
Version: 1.1.9
Summary: Biblioteca Python para análise de qualidade e saúde de código
Home-page: https://github.com/imparcialista/codehealthanalyzer
Author: Luarco Team
Author-email: contato@luarco.com.br
Project-URL: Bug Reports, https://github.com/imparcialista/codehealthanalyzer/issues
Project-URL: Source, https://github.com/imparcialista/codehealthanalyzer
Project-URL: Documentation, https://codehealthanalyzer.readthedocs.io/
Keywords: code-quality,static-analysis,code-health,linting,python,html,css,javascript,ruff,analysis,metrics,reporting
Classifier: Development Status :: 4 - Beta
Classifier: Intended Audience :: Developers
Classifier: Topic :: Software Development :: Quality Assurance
Classifier: Topic :: Software Development :: Testing
Classifier: License :: OSI Approved :: MIT License
Classifier: Programming Language :: Python :: 3
Classifier: Programming Language :: Python :: 3.8
Classifier: Programming Language :: Python :: 3.9
Classifier: Programming Language :: Python :: 3.10
Classifier: Programming Language :: Python :: 3.11
Classifier: Programming Language :: Python :: 3.12
Requires-Python: >=3.8
License-File: LICENSE
Requires-Dist: ruff>=0.1.0
Requires-Dist: click>=8.0.0
Requires-Dist: rich>=12.0.0
Requires-Dist: fastapi>=0.104.0
Requires-Dist: uvicorn[standard]>=0.24.0
Requires-Dist: jinja2>=3.1.0
Requires-Dist: python-multipart>=0.0.6
Requires-Dist: websockets>=12.0
Provides-Extra: dev
Requires-Dist: pytest>=7.0.0; extra == "dev"
Requires-Dist: pytest-cov>=4.0.0; extra == "dev"
Requires-Dist: black>=22.0.0; extra == "dev"
Requires-Dist: isort>=5.0.0; extra == "dev"
Requires-Dist: bandit>=1.7.4; extra == "dev"
Requires-Dist: nox>=2024.4.15; extra == "dev"
Requires-Dist: mypy>=1.0.0; extra == "dev"
Provides-Extra: docs
Requires-Dist: sphinx>=5.0.0; extra == "docs"
Requires-Dist: sphinx-rtd-theme>=1.0.0; extra == "docs"
Provides-Extra: web
Requires-Dist: fastapi>=0.104.0; extra == "web"
Requires-Dist: uvicorn[standard]>=0.24.0; extra == "web"
Requires-Dist: jinja2>=3.1.0; extra == "web"
Requires-Dist: python-multipart>=0.0.6; extra == "web"
Requires-Dist: websockets>=12.0; extra == "web"
Dynamic: author
Dynamic: author-email
Dynamic: classifier
Dynamic: description
Dynamic: description-content-type
Dynamic: home-page
Dynamic: keywords
Dynamic: license-file
Dynamic: project-url
Dynamic: provides-extra
Dynamic: requires-dist
Dynamic: requires-python
Dynamic: summary
